{
	"archive" : {},
	"artifacts" : 
	[
		{
			"path" : "lib/libeasy3d_viewer.a"
		}
	],
	"backtrace" : 1,
	"backtraceGraph" : 
	{
		"commands" : 
		[
			"add_library",
			"target_link_libraries",
			"target_compile_definitions",
			"target_include_directories"
		],
		"files" : 
		[
			"easy3d/viewer/CMakeLists.txt"
		],
		"nodes" : 
		[
			{
				"file" : 0
			},
			{
				"command" : 0,
				"file" : 0,
				"line" : 174,
				"parent" : 0
			},
			{
				"command" : 1,
				"file" : 0,
				"line" : 183,
				"parent" : 0
			},
			{
				"command" : 2,
				"file" : 0,
				"line" : 185,
				"parent" : 0
			},
			{
				"command" : 3,
				"file" : 0,
				"line" : 182,
				"parent" : 0
			}
		]
	},
	"compileGroups" : 
	[
		{
			"compileCommandFragments" : 
			[
				{
					"fragment" : "-g -arch arm64 -isysroot /Library/Developer/CommandLineTools/SDKs/MacOSX11.3.sdk"
				},
				{
					"fragment" : "-std=gnu++11"
				}
			],
			"defines" : 
			[
				{
					"backtrace" : 2,
					"define" : "GLEW_NO_GLU"
				},
				{
					"backtrace" : 3,
					"define" : "GLEW_STATIC"
				}
			],
			"includes" : 
			[
				{
					"backtrace" : 4,
					"path" : "/Users/yitongxia/Desktop/A1_Calibration/A1_Calibration_Code"
				},
				{
					"backtrace" : 4,
					"path" : "/Users/yitongxia/Desktop/A1_Calibration/A1_Calibration_Code/cmake-build-debug"
				},
				{
					"backtrace" : 2,
					"path" : "/Users/yitongxia/Desktop/A1_Calibration/A1_Calibration_Code/3rd_party/glew/include"
				},
				{
					"backtrace" : 2,
					"path" : "/Users/yitongxia/Desktop/A1_Calibration/A1_Calibration_Code/3rd_party/glfw/include"
				},
				{
					"backtrace" : 2,
					"path" : "/Users/yitongxia/Desktop/A1_Calibration/A1_Calibration_Code/3rd_party/glog/.."
				}
			],
			"language" : "CXX",
			"languageStandard" : 
			{
				"backtraces" : 
				[
					1
				],
				"standard" : "11"
			},
			"sourceIndexes" : 
			[
				0,
				1,
				2,
				3,
				4,
				5,
				6,
				7,
				8,
				9,
				10,
				11,
				12,
				13,
				14,
				15,
				16,
				17,
				18,
				19,
				20,
				21,
				22,
				23,
				24,
				25,
				26,
				27
			]
		}
	],
	"dependencies" : 
	[
		{
			"backtrace" : 2,
			"id" : "3rd_glew::@3782b4e7c4f9d2ba2c57"
		},
		{
			"backtrace" : 2,
			"id" : "3rd_glfw::@82eb073f23ca4a565ec2"
		},
		{
			"backtrace" : 2,
			"id" : "3rd_glog::@d3cd30be08f891a1b326"
		},
		{
			"backtrace" : 2,
			"id" : "easy3d_core::@cb35a92cddfea1372b37"
		},
		{
			"backtrace" : 2,
			"id" : "easy3d_fileio::@1ac0250c1f979f6df208"
		},
		{
			"backtrace" : 2,
			"id" : "easy3d_util::@a5cd75459df24341c131"
		}
	],
	"folder" : 
	{
		"name" : "easy3d"
	},
	"id" : "easy3d_viewer::@e94df83b7addc850682d",
	"name" : "easy3d_viewer",
	"nameOnDisk" : "libeasy3d_viewer.a",
	"paths" : 
	{
		"build" : "easy3d/viewer",
		"source" : "easy3d/viewer"
	},
	"sourceGroups" : 
	[
		{
			"name" : "Source Files",
			"sourceIndexes" : 
			[
				0,
				1,
				2,
				3,
				4,
				5,
				6,
				7,
				8,
				9,
				10,
				11,
				12,
				13,
				14,
				15,
				16,
				17,
				18,
				19,
				20,
				21,
				22,
				23,
				24,
				25,
				26,
				27
			]
		},
		{
			"name" : "Header Files",
			"sourceIndexes" : 
			[
				28,
				29,
				30,
				31,
				32,
				33,
				34,
				35,
				36,
				37,
				38,
				39,
				40,
				41,
				42,
				43,
				44,
				45,
				46,
				47,
				48,
				49,
				50,
				51,
				52,
				53,
				54,
				55,
				56
			]
		},
		{
			"name" : "",
			"sourceIndexes" : 
			[
				57,
				58,
				59,
				60,
				61,
				62,
				63,
				64,
				65,
				66,
				67,
				68,
				69,
				70,
				71,
				72,
				73,
				74,
				75,
				76,
				77,
				78,
				79,
				80,
				81,
				82,
				83,
				84,
				85,
				86,
				87,
				88,
				89,
				90,
				91,
				92,
				93,
				94,
				95,
				96,
				97,
				98,
				99,
				100,
				101,
				102,
				103,
				104,
				105,
				106,
				107,
				108,
				109,
				110,
				111,
				112,
				113,
				114,
				115,
				116,
				117,
				118,
				119,
				120,
				121,
				122,
				123,
				124,
				125,
				126,
				127,
				128,
				129,
				130,
				131,
				132,
				133,
				134,
				135,
				136,
				137,
				138,
				139,
				140,
				141,
				142,
				143,
				144,
				145,
				146
			]
		}
	],
	"sources" : 
	[
		{
			"backtrace" : 1,
			"compileGroupIndex" : 0,
			"path" : "easy3d/viewer/camera.cpp",
			"sourceGroupIndex" : 0
		},
		{
			"backtrace" : 1,
			"compileGroupIndex" : 0,
			"path" : "easy3d/viewer/clipping_plane.cpp",
			"sourceGroupIndex" : 0
		},
		{
			"backtrace" : 1,
			"compileGroupIndex" : 0,
			"path" : "easy3d/viewer/constraint.cpp",
			"sourceGroupIndex" : 0
		},
		{
			"backtrace" : 1,
			"compileGroupIndex" : 0,
			"path" : "easy3d/viewer/drawable.cpp",
			"sourceGroupIndex" : 0
		},
		{
			"backtrace" : 1,
			"compileGroupIndex" : 0,
			"path" : "easy3d/viewer/drawable_lines.cpp",
			"sourceGroupIndex" : 0
		},
		{
			"backtrace" : 1,
			"compileGroupIndex" : 0,
			"path" : "easy3d/viewer/drawable_points.cpp",
			"sourceGroupIndex" : 0
		},
		{
			"backtrace" : 1,
			"compileGroupIndex" : 0,
			"path" : "easy3d/viewer/drawable_triangles.cpp",
			"sourceGroupIndex" : 0
		},
		{
			"backtrace" : 1,
			"compileGroupIndex" : 0,
			"path" : "easy3d/viewer/frame.cpp",
			"sourceGroupIndex" : 0
		},
		{
			"backtrace" : 1,
			"compileGroupIndex" : 0,
			"path" : "easy3d/viewer/framebuffer_object.cpp",
			"sourceGroupIndex" : 0
		},
		{
			"backtrace" : 1,
			"compileGroupIndex" : 0,
			"path" : "easy3d/viewer/key_frame_interpolator.cpp",
			"sourceGroupIndex" : 0
		},
		{
			"backtrace" : 1,
			"compileGroupIndex" : 0,
			"path" : "easy3d/viewer/manipulated_camera_frame.cpp",
			"sourceGroupIndex" : 0
		},
		{
			"backtrace" : 1,
			"compileGroupIndex" : 0,
			"path" : "easy3d/viewer/manipulated_frame.cpp",
			"sourceGroupIndex" : 0
		},
		{
			"backtrace" : 1,
			"compileGroupIndex" : 0,
			"path" : "easy3d/viewer/model.cpp",
			"sourceGroupIndex" : 0
		},
		{
			"backtrace" : 1,
			"compileGroupIndex" : 0,
			"path" : "easy3d/viewer/opengl_error.cpp",
			"sourceGroupIndex" : 0
		},
		{
			"backtrace" : 1,
			"compileGroupIndex" : 0,
			"path" : "easy3d/viewer/opengl_info.cpp",
			"sourceGroupIndex" : 0
		},
		{
			"backtrace" : 1,
			"compileGroupIndex" : 0,
			"path" : "easy3d/viewer/primitives.cpp",
			"sourceGroupIndex" : 0
		},
		{
			"backtrace" : 1,
			"compileGroupIndex" : 0,
			"path" : "easy3d/viewer/read_pixel.cpp",
			"sourceGroupIndex" : 0
		},
		{
			"backtrace" : 1,
			"compileGroupIndex" : 0,
			"path" : "easy3d/viewer/renderer.cpp",
			"sourceGroupIndex" : 0
		},
		{
			"backtrace" : 1,
			"compileGroupIndex" : 0,
			"path" : "easy3d/viewer/setting.cpp",
			"sourceGroupIndex" : 0
		},
		{
			"backtrace" : 1,
			"compileGroupIndex" : 0,
			"path" : "easy3d/viewer/shader_manager.cpp",
			"sourceGroupIndex" : 0
		},
		{
			"backtrace" : 1,
			"compileGroupIndex" : 0,
			"path" : "easy3d/viewer/shader_program.cpp",
			"sourceGroupIndex" : 0
		},
		{
			"backtrace" : 1,
			"compileGroupIndex" : 0,
			"path" : "easy3d/viewer/tessellator.cpp",
			"sourceGroupIndex" : 0
		},
		{
			"backtrace" : 1,
			"compileGroupIndex" : 0,
			"path" : "easy3d/viewer/texture.cpp",
			"sourceGroupIndex" : 0
		},
		{
			"backtrace" : 1,
			"compileGroupIndex" : 0,
			"path" : "easy3d/viewer/opengl_timer.cpp",
			"sourceGroupIndex" : 0
		},
		{
			"backtrace" : 1,
			"compileGroupIndex" : 0,
			"path" : "easy3d/viewer/transform.cpp",
			"sourceGroupIndex" : 0
		},
		{
			"backtrace" : 1,
			"compileGroupIndex" : 0,
			"path" : "easy3d/viewer/transform_decompose.cpp",
			"sourceGroupIndex" : 0
		},
		{
			"backtrace" : 1,
			"compileGroupIndex" : 0,
			"path" : "easy3d/viewer/vertex_array_object.cpp",
			"sourceGroupIndex" : 0
		},
		{
			"backtrace" : 1,
			"compileGroupIndex" : 0,
			"path" : "easy3d/viewer/viewer.cpp",
			"sourceGroupIndex" : 0
		},
		{
			"backtrace" : 1,
			"path" : "easy3d/viewer/camera.h",
			"sourceGroupIndex" : 1
		},
		{
			"backtrace" : 1,
			"path" : "easy3d/viewer/clipping_plane.h",
			"sourceGroupIndex" : 1
		},
		{
			"backtrace" : 1,
			"path" : "easy3d/viewer/constraint.h",
			"sourceGroupIndex" : 1
		},
		{
			"backtrace" : 1,
			"path" : "easy3d/viewer/drawable.h",
			"sourceGroupIndex" : 1
		},
		{
			"backtrace" : 1,
			"path" : "easy3d/viewer/drawable_lines.h",
			"sourceGroupIndex" : 1
		},
		{
			"backtrace" : 1,
			"path" : "easy3d/viewer/drawable_points.h",
			"sourceGroupIndex" : 1
		},
		{
			"backtrace" : 1,
			"path" : "easy3d/viewer/drawable_triangles.h",
			"sourceGroupIndex" : 1
		},
		{
			"backtrace" : 1,
			"path" : "easy3d/viewer/frame.h",
			"sourceGroupIndex" : 1
		},
		{
			"backtrace" : 1,
			"path" : "easy3d/viewer/framebuffer_object.h",
			"sourceGroupIndex" : 1
		},
		{
			"backtrace" : 1,
			"path" : "easy3d/viewer/key_frame_interpolator.h",
			"sourceGroupIndex" : 1
		},
		{
			"backtrace" : 1,
			"path" : "easy3d/viewer/manipulated_camera_frame.h",
			"sourceGroupIndex" : 1
		},
		{
			"backtrace" : 1,
			"path" : "easy3d/viewer/manipulated_frame.h",
			"sourceGroupIndex" : 1
		},
		{
			"backtrace" : 1,
			"path" : "easy3d/viewer/model.h",
			"sourceGroupIndex" : 1
		},
		{
			"backtrace" : 1,
			"path" : "easy3d/viewer/opengl.h",
			"sourceGroupIndex" : 1
		},
		{
			"backtrace" : 1,
			"path" : "easy3d/viewer/opengl_error.h",
			"sourceGroupIndex" : 1
		},
		{
			"backtrace" : 1,
			"path" : "easy3d/viewer/opengl_info.h",
			"sourceGroupIndex" : 1
		},
		{
			"backtrace" : 1,
			"path" : "easy3d/viewer/primitives.h",
			"sourceGroupIndex" : 1
		},
		{
			"backtrace" : 1,
			"path" : "easy3d/viewer/read_pixel.h",
			"sourceGroupIndex" : 1
		},
		{
			"backtrace" : 1,
			"path" : "easy3d/viewer/renderer.h",
			"sourceGroupIndex" : 1
		},
		{
			"backtrace" : 1,
			"path" : "easy3d/viewer/setting.h",
			"sourceGroupIndex" : 1
		},
		{
			"backtrace" : 1,
			"path" : "easy3d/viewer/shader_manager.h",
			"sourceGroupIndex" : 1
		},
		{
			"backtrace" : 1,
			"path" : "easy3d/viewer/shader_program.h",
			"sourceGroupIndex" : 1
		},
		{
			"backtrace" : 1,
			"path" : "easy3d/viewer/opengl_timer.h",
			"sourceGroupIndex" : 1
		},
		{
			"backtrace" : 1,
			"path" : "easy3d/viewer/tessellator.h",
			"sourceGroupIndex" : 1
		},
		{
			"backtrace" : 1,
			"path" : "easy3d/viewer/texture.h",
			"sourceGroupIndex" : 1
		},
		{
			"backtrace" : 1,
			"path" : "easy3d/viewer/transform.h",
			"sourceGroupIndex" : 1
		},
		{
			"backtrace" : 1,
			"path" : "easy3d/viewer/transform_decompose.h",
			"sourceGroupIndex" : 1
		},
		{
			"backtrace" : 1,
			"path" : "easy3d/viewer/vertex_array_object.h",
			"sourceGroupIndex" : 1
		},
		{
			"backtrace" : 1,
			"path" : "easy3d/viewer/viewer.h",
			"sourceGroupIndex" : 1
		},
		{
			"backtrace" : 1,
			"path" : "resources/shaders/points/points_plain_color.vert",
			"sourceGroupIndex" : 2
		},
		{
			"backtrace" : 1,
			"path" : "resources/shaders/points/points_plain_color.frag",
			"sourceGroupIndex" : 2
		},
		{
			"backtrace" : 1,
			"path" : "resources/shaders/points/points_plain_texture.vert",
			"sourceGroupIndex" : 2
		},
		{
			"backtrace" : 1,
			"path" : "resources/shaders/points/points_plain_texture.frag",
			"sourceGroupIndex" : 2
		},
		{
			"backtrace" : 1,
			"path" : "resources/shaders/points/points_spheres_geometry_color.vert",
			"sourceGroupIndex" : 2
		},
		{
			"backtrace" : 1,
			"path" : "resources/shaders/points/points_spheres_geometry_color.geom",
			"sourceGroupIndex" : 2
		},
		{
			"backtrace" : 1,
			"path" : "resources/shaders/points/points_spheres_geometry_color.frag",
			"sourceGroupIndex" : 2
		},
		{
			"backtrace" : 1,
			"path" : "resources/shaders/points/points_spheres_geometry_texture.vert",
			"sourceGroupIndex" : 2
		},
		{
			"backtrace" : 1,
			"path" : "resources/shaders/points/points_spheres_geometry_texture.geom",
			"sourceGroupIndex" : 2
		},
		{
			"backtrace" : 1,
			"path" : "resources/shaders/points/points_spheres_geometry_texture.frag",
			"sourceGroupIndex" : 2
		},
		{
			"backtrace" : 1,
			"path" : "resources/shaders/points/points_spheres_sprite_color.vert",
			"sourceGroupIndex" : 2
		},
		{
			"backtrace" : 1,
			"path" : "resources/shaders/points/points_spheres_sprite_color.frag",
			"sourceGroupIndex" : 2
		},
		{
			"backtrace" : 1,
			"path" : "resources/shaders/points/points_surfel_color.vert",
			"sourceGroupIndex" : 2
		},
		{
			"backtrace" : 1,
			"path" : "resources/shaders/points/points_surfel_color.geom",
			"sourceGroupIndex" : 2
		},
		{
			"backtrace" : 1,
			"path" : "resources/shaders/points/points_surfel_color.frag",
			"sourceGroupIndex" : 2
		},
		{
			"backtrace" : 1,
			"path" : "resources/shaders/points/points_surfel_texture.vert",
			"sourceGroupIndex" : 2
		},
		{
			"backtrace" : 1,
			"path" : "resources/shaders/points/points_surfel_texture.geom",
			"sourceGroupIndex" : 2
		},
		{
			"backtrace" : 1,
			"path" : "resources/shaders/points/points_surfel_texture.frag",
			"sourceGroupIndex" : 2
		},
		{
			"backtrace" : 1,
			"path" : "resources/shaders/lines/lines_plain_color.vert",
			"sourceGroupIndex" : 2
		},
		{
			"backtrace" : 1,
			"path" : "resources/shaders/lines/lines_plain_color.frag",
			"sourceGroupIndex" : 2
		},
		{
			"backtrace" : 1,
			"path" : "resources/shaders/lines/lines_plain_texture.vert",
			"sourceGroupIndex" : 2
		},
		{
			"backtrace" : 1,
			"path" : "resources/shaders/lines/lines_plain_texture.frag",
			"sourceGroupIndex" : 2
		},
		{
			"backtrace" : 1,
			"path" : "resources/shaders/lines/lines_plain_color_width_control.vert",
			"sourceGroupIndex" : 2
		},
		{
			"backtrace" : 1,
			"path" : "resources/shaders/lines/lines_plain_color_width_control.geom",
			"sourceGroupIndex" : 2
		},
		{
			"backtrace" : 1,
			"path" : "resources/shaders/lines/lines_plain_color_width_control.frag",
			"sourceGroupIndex" : 2
		},
		{
			"backtrace" : 1,
			"path" : "resources/shaders/lines/lines_plain_texture_width_control.vert",
			"sourceGroupIndex" : 2
		},
		{
			"backtrace" : 1,
			"path" : "resources/shaders/lines/lines_plain_texture_width_control.geom",
			"sourceGroupIndex" : 2
		},
		{
			"backtrace" : 1,
			"path" : "resources/shaders/lines/lines_plain_texture_width_control.frag",
			"sourceGroupIndex" : 2
		},
		{
			"backtrace" : 1,
			"path" : "resources/shaders/lines/lines_cylinders_color.vert",
			"sourceGroupIndex" : 2
		},
		{
			"backtrace" : 1,
			"path" : "resources/shaders/lines/lines_cylinders_color.geom",
			"sourceGroupIndex" : 2
		},
		{
			"backtrace" : 1,
			"path" : "resources/shaders/lines/lines_cylinders_color.frag",
			"sourceGroupIndex" : 2
		},
		{
			"backtrace" : 1,
			"path" : "resources/shaders/lines/lines_cylinders_texture.vert",
			"sourceGroupIndex" : 2
		},
		{
			"backtrace" : 1,
			"path" : "resources/shaders/lines/lines_cylinders_texture.geom",
			"sourceGroupIndex" : 2
		},
		{
			"backtrace" : 1,
			"path" : "resources/shaders/lines/lines_cylinders_texture.frag",
			"sourceGroupIndex" : 2
		},
		{
			"backtrace" : 1,
			"path" : "resources/shaders/lines/lines_cones_color.vert",
			"sourceGroupIndex" : 2
		},
		{
			"backtrace" : 1,
			"path" : "resources/shaders/lines/lines_cones_color.geom",
			"sourceGroupIndex" : 2
		},
		{
			"backtrace" : 1,
			"path" : "resources/shaders/lines/lines_cones_color.frag",
			"sourceGroupIndex" : 2
		},
		{
			"backtrace" : 1,
			"path" : "resources/shaders/lines/lines_cones_texture.vert",
			"sourceGroupIndex" : 2
		},
		{
			"backtrace" : 1,
			"path" : "resources/shaders/lines/lines_cones_texture.geom",
			"sourceGroupIndex" : 2
		},
		{
			"backtrace" : 1,
			"path" : "resources/shaders/lines/lines_cones_texture.frag",
			"sourceGroupIndex" : 2
		},
		{
			"backtrace" : 1,
			"path" : "resources/shaders/surface/surface_color.vert",
			"sourceGroupIndex" : 2
		},
		{
			"backtrace" : 1,
			"path" : "resources/shaders/surface/surface_color.frag",
			"sourceGroupIndex" : 2
		},
		{
			"backtrace" : 1,
			"path" : "resources/shaders/surface/surface_texture.vert",
			"sourceGroupIndex" : 2
		},
		{
			"backtrace" : 1,
			"path" : "resources/shaders/surface/surface_texture.frag",
			"sourceGroupIndex" : 2
		},
		{
			"backtrace" : 1,
			"path" : "resources/shaders/edl/edl_bilateral_filter.vert",
			"sourceGroupIndex" : 2
		},
		{
			"backtrace" : 1,
			"path" : "resources/shaders/edl/edl_bilateral_filter.frag",
			"sourceGroupIndex" : 2
		},
		{
			"backtrace" : 1,
			"path" : "resources/shaders/edl/edl_compose.vert",
			"sourceGroupIndex" : 2
		},
		{
			"backtrace" : 1,
			"path" : "resources/shaders/edl/edl_compose.frag",
			"sourceGroupIndex" : 2
		},
		{
			"backtrace" : 1,
			"path" : "resources/shaders/edl/edl_shade.vert",
			"sourceGroupIndex" : 2
		},
		{
			"backtrace" : 1,
			"path" : "resources/shaders/edl/edl_shade.frag",
			"sourceGroupIndex" : 2
		},
		{
			"backtrace" : 1,
			"path" : "resources/shaders/screen_space/screen_space_color.vert",
			"sourceGroupIndex" : 2
		},
		{
			"backtrace" : 1,
			"path" : "resources/shaders/screen_space/screen_space_color.frag",
			"sourceGroupIndex" : 2
		},
		{
			"backtrace" : 1,
			"path" : "resources/shaders/screen_space/screen_space_texture.frag",
			"sourceGroupIndex" : 2
		},
		{
			"backtrace" : 1,
			"path" : "resources/shaders/screen_space/screen_space_texture.vert",
			"sourceGroupIndex" : 2
		},
		{
			"backtrace" : 1,
			"path" : "resources/shaders/screen_space/screen_space_depth_texture.vert",
			"sourceGroupIndex" : 2
		},
		{
			"backtrace" : 1,
			"path" : "resources/shaders/screen_space/screen_space_depth_texture.frag",
			"sourceGroupIndex" : 2
		},
		{
			"backtrace" : 1,
			"path" : "resources/shaders/shadow/shadow_generate.vert",
			"sourceGroupIndex" : 2
		},
		{
			"backtrace" : 1,
			"path" : "resources/shaders/shadow/shadow_generate.frag",
			"sourceGroupIndex" : 2
		},
		{
			"backtrace" : 1,
			"path" : "resources/shaders/shadow/shadow_rendering.vert",
			"sourceGroupIndex" : 2
		},
		{
			"backtrace" : 1,
			"path" : "resources/shaders/shadow/shadow_rendering.frag",
			"sourceGroupIndex" : 2
		},
		{
			"backtrace" : 1,
			"path" : "resources/shaders/shadow/soft_shadow_generate.vert",
			"sourceGroupIndex" : 2
		},
		{
			"backtrace" : 1,
			"path" : "resources/shaders/shadow/soft_shadow_generate.frag",
			"sourceGroupIndex" : 2
		},
		{
			"backtrace" : 1,
			"path" : "resources/shaders/shadow/soft_shadow_rendering.vert",
			"sourceGroupIndex" : 2
		},
		{
			"backtrace" : 1,
			"path" : "resources/shaders/shadow/soft_shadow_rendering.frag",
			"sourceGroupIndex" : 2
		},
		{
			"backtrace" : 1,
			"path" : "resources/shaders/ssao/blur.vert",
			"sourceGroupIndex" : 2
		},
		{
			"backtrace" : 1,
			"path" : "resources/shaders/ssao/blur.frag",
			"sourceGroupIndex" : 2
		},
		{
			"backtrace" : 1,
			"path" : "resources/shaders/ssao/geometry_pass.vert",
			"sourceGroupIndex" : 2
		},
		{
			"backtrace" : 1,
			"path" : "resources/shaders/ssao/geometry_pass.frag",
			"sourceGroupIndex" : 2
		},
		{
			"backtrace" : 1,
			"path" : "resources/shaders/ssao/ssao.vert",
			"sourceGroupIndex" : 2
		},
		{
			"backtrace" : 1,
			"path" : "resources/shaders/ssao/ssao.frag",
			"sourceGroupIndex" : 2
		},
		{
			"backtrace" : 1,
			"path" : "resources/shaders/transparency/average_color_blend.vert",
			"sourceGroupIndex" : 2
		},
		{
			"backtrace" : 1,
			"path" : "resources/shaders/transparency/average_color_blend.frag",
			"sourceGroupIndex" : 2
		},
		{
			"backtrace" : 1,
			"path" : "resources/shaders/transparency/average_color_init.vert",
			"sourceGroupIndex" : 2
		},
		{
			"backtrace" : 1,
			"path" : "resources/shaders/transparency/average_color_init.frag",
			"sourceGroupIndex" : 2
		},
		{
			"backtrace" : 1,
			"path" : "resources/shaders/transparency/dual_depth_peeling_blend.vert",
			"sourceGroupIndex" : 2
		},
		{
			"backtrace" : 1,
			"path" : "resources/shaders/transparency/dual_depth_peeling_blend.frag",
			"sourceGroupIndex" : 2
		},
		{
			"backtrace" : 1,
			"path" : "resources/shaders/transparency/dual_depth_peeling_final.vert",
			"sourceGroupIndex" : 2
		},
		{
			"backtrace" : 1,
			"path" : "resources/shaders/transparency/dual_depth_peeling_final.frag",
			"sourceGroupIndex" : 2
		},
		{
			"backtrace" : 1,
			"path" : "resources/shaders/transparency/dual_depth_peeling_init.vert",
			"sourceGroupIndex" : 2
		},
		{
			"backtrace" : 1,
			"path" : "resources/shaders/transparency/dual_depth_peeling_init.frag",
			"sourceGroupIndex" : 2
		},
		{
			"backtrace" : 1,
			"path" : "resources/shaders/transparency/dual_depth_peeling_peel_color.vert",
			"sourceGroupIndex" : 2
		},
		{
			"backtrace" : 1,
			"path" : "resources/shaders/transparency/dual_depth_peeling_peel_color.frag",
			"sourceGroupIndex" : 2
		},
		{
			"backtrace" : 1,
			"path" : "resources/shaders/transparency/dual_depth_peeling_peel_texture.vert",
			"sourceGroupIndex" : 2
		},
		{
			"backtrace" : 1,
			"path" : "resources/shaders/transparency/dual_depth_peeling_peel_texture.frag",
			"sourceGroupIndex" : 2
		},
		{
			"backtrace" : 1,
			"path" : "resources/shaders/selection/selection_single_primitive.vert",
			"sourceGroupIndex" : 2
		},
		{
			"backtrace" : 1,
			"path" : "resources/shaders/selection/selection_single_primitive.frag",
			"sourceGroupIndex" : 2
		},
		{
			"backtrace" : 1,
			"path" : "resources/shaders/selection/selection_pointcloud_rect.vert",
			"sourceGroupIndex" : 2
		},
		{
			"backtrace" : 1,
			"path" : "resources/shaders/selection/selection_pointcloud_rect.frag",
			"sourceGroupIndex" : 2
		},
		{
			"backtrace" : 1,
			"path" : "resources/shaders/selection/selection_pointcloud_lasso.vert",
			"sourceGroupIndex" : 2
		},
		{
			"backtrace" : 1,
			"path" : "resources/shaders/selection/selection_pointcloud_lasso.frag",
			"sourceGroupIndex" : 2
		}
	],
	"type" : "STATIC_LIBRARY"
}
